covid19pandas/__init__.py
covid19pandas/download.py
covid19pandas/exceptions.py
covid19pandas/getters.py
covid19pandas/plotters.py
covid19pandas/selectors.py
covid19pandas/utils.py
covid19pandas/version.py
covid19pandas-0.3.1.dist-info/LICENSE.md
covid19pandas-0.3.1.dist-info/METADATA
covid19pandas-0.3.1.dist-info/WHEEL
covid19pandas-0.3.1.dist-info/top_level.txt
covid19pandas-0.3.1.dist-info/RECORD
