Metadata-Version: 2.1
Name: covid19pandas
Version: 0.3.1
Summary: COVID-19 data as pandas dataframes. Built-in plotting functions. Tutorials in our docs.
Home-page: https://github.com/PayneLab/covid19pandas
Author: Dr. Samuel Payne
Author-email: sam_payne@byu.edu
License: Apache 2.0
Project-URL: Documentation, https://github.com/PayneLab/covid19pandas/tree/master/docs/
Keywords: covid covid-19 corona coronavirus COVID COVID-19 pandas Pandas bioinformatics
Platform: UNKNOWN
Classifier: Development Status :: 4 - Beta
Classifier: Intended Audience :: Science/Research
Classifier: Topic :: Scientific/Engineering :: Bio-Informatics
Classifier: License :: OSI Approved :: Apache Software License
Requires-Python: >=3.6.*
Requires-Dist: numpy (>=1.16.3)
Requires-Dist: pandas (>=0.25.1)
Requires-Dist: requests (>=2.21.0)
Requires-Dist: seaborn (>=0.10.0)
Requires-Dist: matplotlib (>=3.1.0)
